transcribe/__init__.py
transcribe/__main__.py
transcribe/application/__init__.py
transcribe/application/protocols.py
transcribe/domain/__init__.py
transcribe/domain/config_loader.py
transcribe/domain/vocabulary.py
transcribe/domain/vocabulary_loader.py
transcribe/infrastructure/__init__.py
transcribe/infrastructure/mock_client.py
transcribe/infrastructure/openai_client.py
transcribe/interface/__init__.py
transcribe/interface/cli.py
whisper_srt-0.4.1.dist-info/licenses/LICENSE
whisper_srt-0.4.1.dist-info/METADATA
whisper_srt-0.4.1.dist-info/WHEEL
whisper_srt-0.4.1.dist-info/entry_points.txt
whisper_srt-0.4.1.dist-info/top_level.txt
whisper_srt-0.4.1.dist-info/RECORD
