Metadata-Version: 2.4
Name: whisper-srt
Version: 0.4.1
Summary: CLI tool to transcribe MP3 audio to SRT subtitles using OpenAI Whisper API
Author-email: tomada1114 <tmasuyama1114@gmail.com>
License: MIT
Project-URL: Homepage, https://github.com/tomada1114/whisper-srt
Project-URL: Repository, https://github.com/tomada1114/whisper-srt
Project-URL: Issues, https://github.com/tomada1114/whisper-srt/issues
Keywords: transcription,whisper,srt,subtitles,audio,openai
Classifier: Development Status :: 4 - Beta
Classifier: Environment :: Console
Classifier: Intended Audience :: End Users/Desktop
Classifier: License :: OSI Approved :: MIT License
Classifier: Operating System :: OS Independent
Classifier: Programming Language :: Python :: 3
Classifier: Programming Language :: Python :: 3.9
Classifier: Programming Language :: Python :: 3.10
Classifier: Programming Language :: Python :: 3.11
Classifier: Programming Language :: Python :: 3.12
Classifier: Topic :: Multimedia :: Sound/Audio :: Speech
Requires-Python: >=3.9
License-File: LICENSE
Requires-Dist: openai>=1.0.0
Requires-Dist: python-dotenv>=1.0.0
Provides-Extra: dev
Requires-Dist: pytest<9.0.0,>=7.4.0; extra == "dev"
Requires-Dist: pytest-mock<4.0.0,>=3.12.0; extra == "dev"
Requires-Dist: pytest-cov<6.0.0,>=4.1.0; extra == "dev"
Requires-Dist: mypy<2.0.0,>=1.7.0; extra == "dev"
Requires-Dist: ruff<1.0.0,>=0.1.0; extra == "dev"
Dynamic: license-file
